__rdflib_hdt_native__.cpython-37m-darwin.so
hdt.cpython-37m-darwin.so
rdflib_hdt/__init__.py
rdflib_hdt/hdt_document.py
rdflib_hdt/hdt_store.py
rdflib_hdt/iterators.py
rdflib_hdt/mapping.py
rdflib_hdt/sparql_op.py
rdflib_hdt/types.py
rdflib_hdt-3.0.dist-info/LICENSE
rdflib_hdt-3.0.dist-info/METADATA
rdflib_hdt-3.0.dist-info/WHEEL
rdflib_hdt-3.0.dist-info/top_level.txt
rdflib_hdt-3.0.dist-info/RECORD
