Metadata-Version: 2.1
Name: rdflib-hdt
Version: 3.0
Summary: A Store back-end for rdflib to allow for reading and querying HDT documents
Home-page: https://github.com/RDFLib/rdflib-hdt
Author: Thomas Minier
Author-email: tminier01@gmail.com
License: MIT
Keywords: rdflib,hdt,rdf,semantic web,search
Platform: UNKNOWN
